my_project_template/__init__.py
my_project_template/create_project_structure.py
my_project_template-0.1.dist-info/LICENSE
my_project_template-0.1.dist-info/METADATA
my_project_template-0.1.dist-info/WHEEL
my_project_template-0.1.dist-info/top_level.txt
my_project_template-0.1.dist-info/RECORD
