Metadata-Version: 2.1
Name: my-project-template
Version: 0.1
Summary: A template that creates a project structure upon installation
Home-page: https://github.com/ravi46931/my_project_template
Author: Your Name
Author-email: your.email@example.com
Classifier: Programming Language :: Python :: 3
Classifier: License :: OSI Approved :: MIT License
Classifier: Operating System :: OS Independent
Requires-Python: >=3.6
License-File: LICENSE
